MANIFEST.in
setup.cfg
setup.py
docs/HISTORY.txt
docs/INSTALL.txt
docs/LICENSE.GPL
docs/LICENSE.txt
sc/__init__.py
sc.social.viewcounter.egg-info/PKG-INFO
sc.social.viewcounter.egg-info/SOURCES.txt
sc.social.viewcounter.egg-info/dependency_links.txt
sc.social.viewcounter.egg-info/entry_points.txt
sc.social.viewcounter.egg-info/namespace_packages.txt
sc.social.viewcounter.egg-info/not-zip-safe
sc.social.viewcounter.egg-info/requires.txt
sc.social.viewcounter.egg-info/top_level.txt
sc/social/__init__.py
sc/social/viewcounter/README.txt
sc/social/viewcounter/__init__.py
sc/social/viewcounter/configure.zcml
sc/social/viewcounter/interfaces.py
sc/social/viewcounter/pageview.py
sc/social/viewcounter/setuphandlers.py
sc/social/viewcounter/version.txt
sc/social/viewcounter/browser/__init__.py
sc/social/viewcounter/browser/configure.zcml
sc/social/viewcounter/browser/portlet.pt
sc/social/viewcounter/browser/portlet.py
sc/social/viewcounter/browser/viewcounter.py
sc/social/viewcounter/browser/viewlets.py
sc/social/viewcounter/controlpanel/__init__.py
sc/social/viewcounter/controlpanel/configure.zcml
sc/social/viewcounter/controlpanel/viewcounter.py
sc/social/viewcounter/docs/browser.txt
sc/social/viewcounter/docs/caching.txt
sc/social/viewcounter/docs/integration.txt
sc/social/viewcounter/docs/portlet.txt
sc/social/viewcounter/profiles/default/actionicons.xml
sc/social/viewcounter/profiles/default/componentregistry.xml
sc/social/viewcounter/profiles/default/controlpanel.xml
sc/social/viewcounter/profiles/default/import_steps.xml
sc/social/viewcounter/profiles/default/metadata.xml
sc/social/viewcounter/profiles/default/portlets.xml
sc/social/viewcounter/profiles/default/propertiestool.xml
sc/social/viewcounter/profiles/default/sc.social.viewcounter.txt
sc/social/viewcounter/profiles/default/viewlets.xml
sc/social/viewcounter/tests/__init__.py
sc/social/viewcounter/tests/testing.zcml
sc/social/viewcounter/tests/tests.py