Metadata-Version: 1.0
Name: sc.social.viewcounter
Version: 1.0.6
Summary: Logger and reporter for page views
Home-page: http://www.simplesconsultoria.com.br
Author: Simples Consultoria
Author-email: products@simplesconsultoria.com.br
License: GPL
Keywords: plone socialtools ranking access
Platform: UNKNOWN
Classifier: Framework :: Plone
Classifier: Programming Language :: Python
Classifier: Topic :: Software Development :: Libraries :: Python Modules
